{"pear-dbmigrator\/dbmigrator":{"versions":{"0.0.1":{"name":"pear-dbmigrator\/dbmigrator","description":"One-line summary of your PEAR package","dist":{"type":"pear","url":"http:\/\/eugenix.github.com\/pear\/get\/dbmigrator-0.0.1.tgz"},"version":"0.0.1","time":"2013-03-21T18:01:55+04:00","require":{"php":">=5.0.0"},"authors":[{"name":"Eugene Kurbatov","email":"ekur@i-loto.ru","homepage":""}],"autoload":{"classmap":{"0":"rest\/c","4":"rest\/m\/allmaintainers.xml","5":"rest\/p\/packages.xml","6":"channel.xml","7":"feed.xml","8":"index.html","9":"packages.json","10":"pearfarm.spec","11":"pirum.css","12":"pirum.xml"}}}},"name":"pear-dbmigrator\/dbmigrator","description":"One-line summary of your PEAR package","maintainers":[{"name":"Eugene Kurbatov","email":"ekur@i-loto.ru","homepage":""}]}}